{"__type__":"cc.SkeletonAnimationClip","_name":"Jump_Front1","_native":".bin","_duration":0.6666666865348816,"sample":30,"wrapMode":2,"description":{"root/Bip001_Red":{"position":{"offset":0,"frameCount":17},"quat":{"offset":68,"frameCount":1},"scale":{"offset":73,"frameCount":1}},"root/Bip001_Red/Bip001 Footsteps":{"position":{"offset":77,"frameCount":16},"quat":{"offset":141,"frameCount":1},"scale":{"offset":146,"frameCount":1}},"root/Bip001_Red/Bip001 Pelvis":{"quat":{"offset":150,"frameCount":17},"scale":{"offset":235,"frameCount":1},"position":{"offset":239,"frameCount":1}},"root/Bip001_Red/Bip001 Pelvis/Bip001 Spine":{"position":{"offset":243,"frameCount":8},"quat":{"offset":275,"frameCount":17},"scale":{"offset":360,"frameCount":1}},"root/Bip001_Red/Bip001 Pelvis/Bip001 Spine/Bip001 L Thigh":{"position":{"offset":364,"frameCount":14},"quat":{"offset":420,"frameCount":17},"scale":{"offset":505,"frameCount":1}},"root/Bip001_Red/Bip001 Pelvis/Bip001 Spine/Bip001 L Thigh/Bip001 L Calf":{"quat":{"offset":509,"frameCount":17},"scale":{"offset":594,"frameCount":1},"position":{"offset":598,"frameCount":1}},"root/Bip001_Red/Bip001 Pelvis/Bip001 Spine/Bip001 L Thigh/Bip001 L Calf/Bip001 L Foot":{"quat":{"offset":602,"frameCount":17},"scale":{"offset":687,"frameCount":1},"position":{"offset":691,"frameCount":1}},"root/Bip001_Red/Bip001 Pelvis/Bip001 Spine/Bip001 L Thigh/Bip001 L Calf/Bip001 L Foot/Bip001 L Toe0":{"quat":{"offset":695,"frameCount":12},"scale":{"offset":755,"frameCount":1},"position":{"offset":759,"frameCount":1}},"root/Bip001_Red/Bip001 Pelvis/Bip001 Spine/Bip001 R Thigh":{"position":{"offset":763,"frameCount":16},"quat":{"offset":827,"frameCount":17},"scale":{"offset":912,"frameCount":1}},"root/Bip001_Red/Bip001 Pelvis/Bip001 Spine/Bip001 R Thigh/Bip001 R Calf":{"quat":{"offset":916,"frameCount":16},"scale":{"offset":996,"frameCount":1},"position":{"offset":1000,"frameCount":1}},"root/Bip001_Red/Bip001 Pelvis/Bip001 Spine/Bip001 R Thigh/Bip001 R Calf/Bip001 R Foot":{"quat":{"offset":1004,"frameCount":17},"scale":{"offset":1089,"frameCount":1},"position":{"offset":1093,"frameCount":1}},"root/Bip001_Red/Bip001 Pelvis/Bip001 Spine/Bip001 R Thigh/Bip001 R Calf/Bip001 R Foot/Bip001 R Toe0":{"quat":{"offset":1097,"frameCount":12},"scale":{"offset":1157,"frameCount":1},"position":{"offset":1161,"frameCount":1}},"root/Bip001_Red/Bip001 Pelvis/Bip001 Spine/Bip001 Spine1":{"position":{"offset":1165,"frameCount":2},"quat":{"offset":1173,"frameCount":17},"scale":{"offset":1258,"frameCount":1}},"root/Bip001_Red/Bip001 Pelvis/Bip001 Spine/Bip001 Spine1/Bip001 Neck":{"quat":{"offset":1262,"frameCount":3},"scale":{"offset":1277,"frameCount":1},"position":{"offset":1281,"frameCount":1}},"root/Bip001_Red/Bip001 Pelvis/Bip001 Spine/Bip001 Spine1/Bip001 Neck/Bip001 L Clavicle":{"position":{"offset":1285,"frameCount":2},"quat":{"offset":1293,"frameCount":17},"scale":{"offset":1378,"frameCount":1}},"root/Bip001_Red/Bip001 Pelvis/Bip001 Spine/Bip001 Spine1/Bip001 Neck/Bip001 L Clavicle/Bip001 L UpperArm":{"quat":{"offset":1382,"frameCount":17},"scale":{"offset":1467,"frameCount":1},"position":{"offset":1471,"frameCount":1}},"root/Bip001_Red/Bip001 Pelvis/Bip001 Spine/Bip001 Spine1/Bip001 Neck/Bip001 L Clavicle/Bip001 L UpperArm/Bip001 L Forearm":{"quat":{"offset":1475,"frameCount":16},"scale":{"offset":1555,"frameCount":1},"position":{"offset":1559,"frameCount":1}},"root/Bip001_Red/Bip001 Pelvis/Bip001 Spine/Bip001 Spine1/Bip001 Neck/Bip001 L Clavicle/Bip001 L UpperArm/Bip001 L Forearm/Bip001 L Hand":{"quat":{"offset":1563,"frameCount":16},"scale":{"offset":1643,"frameCount":1},"position":{"offset":1647,"frameCount":1}},"root/Bip001_Red/Bip001 Pelvis/Bip001 Spine/Bip001 Spine1/Bip001 Neck/Bip001 R Clavicle":{"position":{"offset":1651,"frameCount":2},"quat":{"offset":1659,"frameCount":17},"scale":{"offset":1744,"frameCount":1}},"root/Bip001_Red/Bip001 Pelvis/Bip001 Spine/Bip001 Spine1/Bip001 Neck/Bip001 R Clavicle/Bip001 R UpperArm":{"quat":{"offset":1748,"frameCount":17},"scale":{"offset":1833,"frameCount":1},"position":{"offset":1837,"frameCount":1}},"root/Bip001_Red/Bip001 Pelvis/Bip001 Spine/Bip001 Spine1/Bip001 Neck/Bip001 R Clavicle/Bip001 R UpperArm/Bip001 R Forearm":{"quat":{"offset":1841,"frameCount":17},"scale":{"offset":1926,"frameCount":1},"position":{"offset":1930,"frameCount":1}},"root/Bip001_Red/Bip001 Pelvis/Bip001 Spine/Bip001 Spine1/Bip001 Neck/Bip001 R Clavicle/Bip001 R UpperArm/Bip001 R Forearm/Bip001 R Hand":{"quat":{"offset":1934,"frameCount":17},"scale":{"offset":2019,"frameCount":1},"position":{"offset":2023,"frameCount":1}},"root/Bip001_Red/Bip001 Pelvis/Bip001 Spine/Bip001 Spine1/Bip001 Neck/Bip001 Head":{"quat":{"offset":2027,"frameCount":17},"scale":{"offset":2112,"frameCount":1},"position":{"offset":2116,"frameCount":1}},"root/Bip001_Red/Bip001 Pelvis/Bip001 Spine/Bip001 Spine1/Bip001 Neck/Bip001 Head/p1_Bone001(mirrored)":{"quat":{"offset":2120,"frameCount":17},"scale":{"offset":2205,"frameCount":1},"position":{"offset":2209,"frameCount":1}},"root/Bip001_Red/Bip001 Pelvis/Bip001 Spine/Bip001 Spine1/Bip001 Neck/Bip001 Head/p1_Bone001(mirrored)/p1_Bone002(mirrored)":{"quat":{"offset":2213,"frameCount":17},"scale":{"offset":2298,"frameCount":1},"position":{"offset":2302,"frameCount":1}},"root/Bip001_Red/Bip001 Pelvis/Bip001 Spine/Bip001 Spine1/Bip001 Neck/Bip001 Head/p1_Bone001(mirrored)/p1_Bone002(mirrored)/p1_Bone003(mirrored)":{"quat":{"offset":2306,"frameCount":17},"scale":{"offset":2391,"frameCount":1},"position":{"offset":2395,"frameCount":1}},"root/Bip001_Red/Bip001 Pelvis/Bip001 Spine/Bip001 Spine1/Bip001 Neck/Bip001 Head/p1_Bone001":{"quat":{"offset":2399,"frameCount":17},"scale":{"offset":2484,"frameCount":1},"position":{"offset":2488,"frameCount":1}},"root/Bip001_Red/Bip001 Pelvis/Bip001 Spine/Bip001 Spine1/Bip001 Neck/Bip001 Head/p1_Bone001/p1_Bone002":{"quat":{"offset":2492,"frameCount":17},"scale":{"offset":2577,"frameCount":1},"position":{"offset":2581,"frameCount":1}},"root/Bip001_Red/Bip001 Pelvis/Bip001 Spine/Bip001 Spine1/Bip001 Neck/Bip001 Head/p1_Bone001/p1_Bone002/p1_Bone003":{"quat":{"offset":2585,"frameCount":17},"scale":{"offset":2670,"frameCount":1},"position":{"offset":2674,"frameCount":1}},"root/Bip001_Red/Bip001 Pelvis/Bip001 Spine/Bip001 Spine1/Bip001 Neck/Bip001 Head/ChuNv_HeadBone003":{"quat":{"offset":2678,"frameCount":16},"scale":{"offset":2758,"frameCount":1},"position":{"offset":2762,"frameCount":1}},"root/Bip001_Red/Bip001 Pelvis/Bip001 Spine/Bip001 Spine1/Bip001 Neck/Bip001 Head/ChuNv_HeadBone003/ChuNv_HeadBone004":{"quat":{"offset":2766,"frameCount":17},"scale":{"offset":2851,"frameCount":1},"position":{"offset":2855,"frameCount":1}},"root/Bip001_Red/Bip001 Pelvis/Bip001 Spine/Bip001 Spine1/ChuNv_RBone001":{"quat":{"offset":2859,"frameCount":17},"scale":{"offset":2944,"frameCount":1},"position":{"offset":2948,"frameCount":1}},"root/Bip001_Red/Bip001 Pelvis/Bip001 Spine/Bip001 Spine1/ChuNv_RBone001/ChuNv_RBone002":{"quat":{"offset":2952,"frameCount":15},"scale":{"offset":3027,"frameCount":1},"position":{"offset":3031,"frameCount":1}},"root/Bip001_Red/Bip001 Pelvis/Bip001 Spine/Bip001 Spine1/ChuNv_LBone001":{"quat":{"offset":3035,"frameCount":17},"scale":{"offset":3120,"frameCount":1},"position":{"offset":3124,"frameCount":1}},"root/Bip001_Red/Bip001 Pelvis/Bip001 Spine/Bip001 Spine1/ChuNv_LBone001/ChuNv_LBone002":{"quat":{"offset":3128,"frameCount":15},"scale":{"offset":3203,"frameCount":1},"position":{"offset":3207,"frameCount":1}},"Body_p3":{"quat":{"offset":3211,"frameCount":1},"scale":{"offset":3216,"frameCount":1},"position":{"offset":3220,"frameCount":1}},"root":{"quat":{"offset":3224,"frameCount":1},"scale":{"offset":3229,"frameCount":1},"position":{"offset":3233,"frameCount":1}},"root/Bip001_Red/Bip001 Pelvis/Bip001 Spine/Bip001 L Thigh/Bip001 L Calf/Bip001 L Foot/Bip001 L Toe0/Bip001 L Toe0Nub":{"quat":{"offset":3237,"frameCount":1},"scale":{"offset":3242,"frameCount":1},"position":{"offset":3246,"frameCount":1}},"root/Bip001_Red/Bip001 Pelvis/Bip001 Spine/Bip001 R Thigh/Bip001 R Calf/Bip001 R Foot/Bip001 R Toe0/Bip001 R Toe0Nub":{"quat":{"offset":3250,"frameCount":1},"scale":{"offset":3255,"frameCount":1},"position":{"offset":3259,"frameCount":1}},"root/Bip001_Red/Bip001 Pelvis/Bip001 Spine/Bip001 Spine1/Bip001 Neck/Bip001 L Clavicle/Bip001 L UpperArm/Bip001 L Forearm/Bip001 L Hand/Bip001 L Finger0":{"quat":{"offset":3263,"frameCount":1},"scale":{"offset":3268,"frameCount":1},"position":{"offset":3272,"frameCount":1}},"root/Bip001_Red/Bip001 Pelvis/Bip001 Spine/Bip001 Spine1/Bip001 Neck/Bip001 L Clavicle/Bip001 L UpperArm/Bip001 L Forearm/Bip001 L Hand/Bip001 L Finger0/Bip001 L Finger0Nub":{"quat":{"offset":3276,"frameCount":1},"scale":{"offset":3281,"frameCount":1},"position":{"offset":3285,"frameCount":1}},"root/Bip001_Red/Bip001 Pelvis/Bip001 Spine/Bip001 Spine1/Bip001 Neck/Bip001 R Clavicle/Bip001 R UpperArm/Bip001 R Forearm/Bip001 R Hand/Bip001 R Finger0":{"quat":{"offset":3289,"frameCount":1},"scale":{"offset":3294,"frameCount":1},"position":{"offset":3298,"frameCount":1}},"root/Bip001_Red/Bip001 Pelvis/Bip001 Spine/Bip001 Spine1/Bip001 Neck/Bip001 R Clavicle/Bip001 R UpperArm/Bip001 R Forearm/Bip001 R Hand/Bip001 R Finger0/Bip001 R Finger0Nub":{"quat":{"offset":3302,"frameCount":1},"scale":{"offset":3307,"frameCount":1},"position":{"offset":3311,"frameCount":1}},"root/Bip001_Red/Bip001 Pelvis/Bip001 Spine/Bip001 Spine1/Bip001 Neck/Bip001 R Clavicle/Bip001 R UpperArm/Bip001 R Forearm/Bip001 R Hand/p3_HuaTongBone001":{"quat":{"offset":3315,"frameCount":1},"scale":{"offset":3320,"frameCount":1},"position":{"offset":3324,"frameCount":1}},"root/Bip001_Red/Bip001 Pelvis/Bip001 Spine/Bip001 Spine1/Bip001 Neck/Bip001 Head/Bip001 HeadNub":{"quat":{"offset":3328,"frameCount":1},"scale":{"offset":3333,"frameCount":1},"position":{"offset":3337,"frameCount":1}},"root/Bip001_Red/Bip001 Pelvis/Bip001 Spine/Bip001 Spine1/Bip001 Neck/Bip001 Head/p2_Bone001":{"quat":{"offset":3341,"frameCount":1},"scale":{"offset":3346,"frameCount":1},"position":{"offset":3350,"frameCount":1}},"root/Bip001_Red/Bip001 Pelvis/Bip001 Spine/Bip001 Spine1/Bip001 Neck/Bip001 Head/p2_Bone001/p2_Bone002":{"quat":{"offset":3354,"frameCount":1},"scale":{"offset":3359,"frameCount":1},"position":{"offset":3363,"frameCount":1}},"root/Bip001_Red/Bip001 Pelvis/Bip001 Spine/Bip001 Spine1/Bip001 Neck/Bip001 Head/p2_Bone001/p2_Bone002/p2_Bone003":{"quat":{"offset":3367,"frameCount":1},"scale":{"offset":3372,"frameCount":1},"position":{"offset":3376,"frameCount":1}}}}