[{"__type__":"cc.Prefab","_name":"Role1_2","data":{"__id__":1}},{"__type__":"cc.Node","_name":"Role4_2","_children":[{"__id__":2},{"__id__":3},{"__id__":23}],"_components":[{"__type__":"cc.SkeletonAnimation","node":{"__id__":1},"_clips":[{"__uuid__":"0aSRBfp3xHgJbceXaEVC95"},{"__uuid__":"0fZKbaQKFFarYZ+kVC8bCu"},{"__uuid__":"fcUXfvRepJGKpLJrfVt/Oh"},{"__uuid__":"c82x4YOHhCx6b4BkqNSduR"},{"__uuid__":"17YD4leGlCDINi8okHtO12"},{"__uuid__":"745ZxlzudEXbmKn9DFeZAS"},{"__uuid__":"3fQcEpff5K6o6MiRzsWNS2"},{"__uuid__":"0bQv4o7ytB8rtcPNNKvJnd"},{"__uuid__":"15vDKuDQBMxqH1sBjTf92g"}],"_model":{"__uuid__":"70g0ErlDdK6pgNvIoYHAU9"}}],"_prefab":{"__type__":"cc.PrefabInfo","root":{"__id__":1},"asset":{"__uuid__":"65olQUWkxLHKiaTOYyk9UO"},"fileId":"b70ZdrBqVGyoFGHgEHDssI"},"_trs":{"__type__":"TypedArray","ctor":"Float64Array","array":[0,0,0,0,-1,0,6.123233995736766e-17,270,270,270]},"_eulerAngles":{"__type__":"cc.Vec3","y":-180},"_is3DNode":true},{"__type__":"cc.Node","_name":"Body","_parent":{"__id__":1},"_components":[{"__type__":"cc.SkinnedMeshRenderer","node":{"__id__":2},"_materials":[{"__uuid__":"fc+K6y3fVNv4tpLDAfjFXj"}],"_mesh":{"__uuid__":"0d6C6WjGdDYpJwS7b4Rr3w"},"_skeleton":{"__uuid__":"f084Uok1BGFbKdpI9biDs0"},"_rootBone":{"__id__":1}}],"_prefab":{"__type__":"cc.PrefabInfo","root":{"__id__":1},"asset":{"__uuid__":"65olQUWkxLHKiaTOYyk9UO"},"fileId":"02JSmVvHdGYZdeDFVt9FdW"},"_trs":{"__type__":"TypedArray","ctor":"Float64Array","array":[0,0,0,-0.7071067690849295,0,0,0.7071067932881653,2.53999996185303,2.53999996185303,2.53999996185303]},"_eulerAngles":{"__type__":"cc.Vec3","x":-89.99999803884887},"_is3DNode":true},{"__type__":"cc.Node","_name":"root","_parent":{"__id__":1},"_children":[{"__id__":4}],"_prefab":{"__type__":"cc.PrefabInfo","root":{"__id__":1},"asset":{"__uuid__":"65olQUWkxLHKiaTOYyk9UO"},"fileId":"99NzMSSZRKR6NPa0J+QmjO"},"_trs":{"__type__":"TypedArray","ctor":"Float64Array","array":[0,0,0,2.1855694143369007e-8,0,0,0.9999999999999998,2.53999996185303,2.53999996185303,2.53999996185303]},"_eulerAngles":{"__type__":"cc.Vec3","x":0.000002504478065487671},"_is3DNode":true},{"__type__":"cc.Node","_name":"Bip001_Red","_parent":{"__id__":3},"_children":[{"__id__":5}],"_prefab":{"__type__":"cc.PrefabInfo","root":{"__id__":1},"asset":{"__uuid__":"65olQUWkxLHKiaTOYyk9UO"},"fileId":"8e61BtHAlKc6ST7OU8xkRb"},"_trs":{"__type__":"TypedArray","ctor":"Float64Array","array":[0.0234133899211884,0.108835779130459,0.00383885833434761,-0.5048496075856936,-0.4951029071593956,-0.4951028876133551,0.5048495971275041,1,1,1]},"_eulerAngles":{"__type__":"cc.Vec3","x":-89.99999949608494,"y":-88.88309219756879,"z":0.000001724109156354372},"_is3DNode":true},{"__type__":"cc.Node","_name":"Bip001 Pelvis","_parent":{"__id__":4},"_children":[{"__id__":6}],"_prefab":{"__type__":"cc.PrefabInfo","root":{"__id__":1},"asset":{"__uuid__":"65olQUWkxLHKiaTOYyk9UO"},"fileId":"f9DPhtm7VE8LkhzFJvIFBv"},"_trs":{"__type__":"TypedArray","ctor":"Float64Array","array":[0,0,0,-0.49999999254919475,-0.49999999254919475,-0.4999993219974208,0.5000006929032498,1,1,1]},"_eulerAngles":{"__type__":"cc.Vec3","x":-89.99992145288073,"y":-89.99992145288073,"z":-0.0000017074910921019665},"_is3DNode":true},{"__type__":"cc.Node","_name":"Bip001 Spine","_parent":{"__id__":5},"_children":[{"__id__":7},{"__id__":10},{"__id__":13}],"_prefab":{"__type__":"cc.PrefabInfo","root":{"__id__":1},"asset":{"__uuid__":"65olQUWkxLHKiaTOYyk9UO"},"fileId":"f33q9HbZpID6ZTyzVcs983"},"_trs":{"__type__":"TypedArray","ctor":"Float64Array","array":[0.0182135198265314,-0.0000198999041458592,2.62260435590633e-8,-0.0000021327814408777004,-7.510793665209784e-7,0.08755242057204823,0.9961599136920047,1,1,1]},"_eulerAngles":{"__type__":"cc.Vec3","x":-0.00023959807556917203,"y":-0.00006534087869483691,"z":10.045630360798306},"_is3DNode":true},{"__type__":"cc.Node","_name":"Bip001 L Thigh","_parent":{"__id__":6},"_children":[{"__id__":8}],"_prefab":{"__type__":"cc.PrefabInfo","root":{"__id__":1},"asset":{"__uuid__":"65olQUWkxLHKiaTOYyk9UO"},"fileId":"53nQIuIFlGfpLY/lXQzQ6s"},"_trs":{"__type__":"TypedArray","ctor":"Float64Array","array":[-0.0179308131337166,0.00319656357169151,0.0226948298513889,0.22162427740752555,0.9623408027088091,0.02607949308442572,0.15525050449456382,1,1,1]},"_eulerAngles":{"__type__":"cc.Vec3","x":1.1846737674942758,"y":161.40039538675163,"z":25.76327170614999},"_is3DNode":true},{"__type__":"cc.Node","_name":"Bip001 L Calf","_parent":{"__id__":7},"_children":[{"__id__":9}],"_prefab":{"__type__":"cc.PrefabInfo","root":{"__id__":1},"asset":{"__uuid__":"65olQUWkxLHKiaTOYyk9UO"},"fileId":"42lYoytSdEgakYVB2t9RDQ"},"_trs":{"__type__":"TypedArray","ctor":"Float64Array","array":[0.0585832446813583,0,3.57627860658738e-9,2.6618769013550554e-17,3.7868695608691484e-17,-0.3763801881499243,0.9264653010060483,1,1,1]},"_eulerAngles":{"__type__":"cc.Vec3","x":6.222144305457454e-15,"y":7.21162973423402e-15,"z":-44.219285211571965},"_is3DNode":true},{"__type__":"cc.Node","_name":"Bip001 L Foot","_parent":{"__id__":8},"_children":[{"__type__":"cc.Node","_name":"Bip001 L Toe0","_parent":{"__id__":9},"_prefab":{"__type__":"cc.PrefabInfo","root":{"__id__":1},"asset":{"__uuid__":"65olQUWkxLHKiaTOYyk9UO"},"fileId":"b8xkHZ9htHdqWI3xPX0C2l"},"_trs":{"__type__":"TypedArray","ctor":"Float64Array","array":[0.0129501316696405,0.0234496351331472,0,-8.612235045441152e-8,-8.612235045441153e-8,0.7071067811865422,0.7071067811865424,1,1,1]},"_eulerAngles":{"__type__":"cc.Vec3","y":-0.000013956724313983303,"z":90},"_is3DNode":true}],"_prefab":{"__type__":"cc.PrefabInfo","root":{"__id__":1},"asset":{"__uuid__":"65olQUWkxLHKiaTOYyk9UO"},"fileId":"46GGhIA6BMQ7mdxhF8cyvM"},"_trs":{"__type__":"TypedArray","ctor":"Float64Array","array":[0.0511104874312878,-2.22044599961948e-18,1.19209286886246e-9,-0.04878548968311225,0.14890031359242847,0.24611569506073058,0.9564913681017873,1,1,1]},"_eulerAngles":{"__type__":"cc.Vec3","x":-10.792210534747134,"y":20.309800890984757,"z":27.147755069802983},"_is3DNode":true},{"__type__":"cc.Node","_name":"Bip001 R Thigh","_parent":{"__id__":6},"_children":[{"__id__":11}],"_prefab":{"__type__":"cc.PrefabInfo","root":{"__id__":1},"asset":{"__uuid__":"65olQUWkxLHKiaTOYyk9UO"},"fileId":"36s2/bw/5AIpP8v/uPuS+4"},"_trs":{"__type__":"TypedArray","ctor":"Float64Array","array":[-0.0179308131337166,0.0031966888345778,-0.022694805637002,0.43782702966030856,0.8588695996741308,0.10043313096170421,0.24609690989457497,1,1,1]},"_eulerAngles":{"__type__":"cc.Vec3","x":4.12144418666566,"y":145.9543240672236,"z":53.274081416268665},"_is3DNode":true},{"__type__":"cc.Node","_name":"Bip001 R Calf","_parent":{"__id__":10},"_children":[{"__id__":12}],"_prefab":{"__type__":"cc.PrefabInfo","root":{"__id__":1},"asset":{"__uuid__":"65olQUWkxLHKiaTOYyk9UO"},"fileId":"5e4vO850JKIIoM16l3gJCh"},"_trs":{"__type__":"TypedArray","ctor":"Float64Array","array":[0.0585832446813583,4.76837147544984e-9,4.76837147544984e-9,-8.322903927296916e-17,8.322903927296916e-17,0.8748631077204484,-0.4843702537829085,1,1,1]},"_eulerAngles":{"__type__":"cc.Vec3","x":-180,"y":180,"z":-57.94244277618284},"_is3DNode":true},{"__type__":"cc.Node","_name":"Bip001 R Foot","_parent":{"__id__":11},"_children":[{"__type__":"cc.Node","_name":"Bip001 R Toe0","_parent":{"__id__":12},"_prefab":{"__type__":"cc.PrefabInfo","root":{"__id__":1},"asset":{"__uuid__":"65olQUWkxLHKiaTOYyk9UO"},"fileId":"ecG2whAw5JJIIlA8eDd8An"},"_trs":{"__type__":"TypedArray","ctor":"Float64Array","array":[0.0129501288756728,0.0234496351331472,2.38418573772492e-9,5.597629233785682e-7,5.597629233785683e-7,0.707106781186326,0.7071067811863261,1,1,1]},"_eulerAngles":{"__type__":"cc.Vec3","y":0.00009071346475756399,"z":90},"_is3DNode":true}],"_prefab":{"__type__":"cc.PrefabInfo","root":{"__id__":1},"asset":{"__uuid__":"65olQUWkxLHKiaTOYyk9UO"},"fileId":"9ecAX8xj1Gdq/8+TTBHcgs"},"_trs":{"__type__":"TypedArray","ctor":"Float64Array","array":[0.0511104911565781,8.88178399847791e-18,-8.88178399847791e-18,-0.18414987522432982,0.15942822341619003,0.2411124360268459,0.9394340095112702,1,1,1]},"_eulerAngles":{"__type__":"cc.Vec3","x":-27.39708992693019,"y":24.997795389026788,"z":23.222390726193773},"_is3DNode":true},{"__type__":"cc.Node","_name":"Bip001 Spine1","_parent":{"__id__":6},"_children":[{"__id__":14}],"_prefab":{"__type__":"cc.PrefabInfo","root":{"__id__":1},"asset":{"__uuid__":"65olQUWkxLHKiaTOYyk9UO"},"fileId":"6fZKb3UkdBT60u7xs2pL3L"},"_trs":{"__type__":"TypedArray","ctor":"Float64Array","array":[0.0253856275230646,-0.0000205600263143424,8.88178399847791e-18,-6.84323708810552e-10,2.52967452540886e-10,1.73111621887365e-19,1,1,1,1]},"_eulerAngles":{"__type__":"cc.Vec3","x":-7.841772067116827e-8,"y":2.8987934769537443e-8,"z":-3.9462713262436243e-25},"_is3DNode":true},{"__type__":"cc.Node","_name":"Bip001 Neck","_parent":{"__id__":13},"_children":[{"__id__":15},{"__id__":19},{"__type__":"cc.Node","_name":"Bip001 Head","_parent":{"__id__":14},"_prefab":{"__type__":"cc.PrefabInfo","root":{"__id__":1},"asset":{"__uuid__":"65olQUWkxLHKiaTOYyk9UO"},"fileId":"48HLWaTNhJlbEfpkxIdv8O"},"_trs":{"__type__":"TypedArray","ctor":"Float64Array","array":[0.030070761218667,2.38418573772492e-9,-4.44089199923895e-18,-0.034820441356269126,0.0051826346583003025,-0.1372001476977472,0.9899175706256909,1,1,1]},"_eulerAngles":{"__type__":"cc.Vec3","x":-4.023280674346177,"y":0.04203697723346607,"z":-15.78299153425151},"_is3DNode":true}],"_prefab":{"__type__":"cc.PrefabInfo","root":{"__id__":1},"asset":{"__uuid__":"65olQUWkxLHKiaTOYyk9UO"},"fileId":"00tEo5sRhBF6tZzL1t27Nw"},"_trs":{"__type__":"TypedArray","ctor":"Float64Array","array":[0.0258184801787138,-0.0000238215925492113,-9.53674295089968e-9,0.0002531782604163269,-0.00042002600396286903,0.05004622640244996,0.9987467820733136,1,1,1]},"_eulerAngles":{"__type__":"cc.Vec3","x":0.03154253507660972,"y":-0.04977238857219182,"z":5.737258819551834},"_is3DNode":true},{"__type__":"cc.Node","_name":"Bip001 L Clavicle","_parent":{"__id__":14},"_children":[{"__id__":16}],"_prefab":{"__type__":"cc.PrefabInfo","root":{"__id__":1},"asset":{"__uuid__":"65olQUWkxLHKiaTOYyk9UO"},"fileId":"3a75La0OtLZ7exdl7ncbND"},"_trs":{"__type__":"TypedArray","ctor":"Float64Array","array":[0.00000568389896216104,0.0000269722931989236,0.00657659769058228,0.7065033550051998,-0.03549093125847189,0.7059096097252557,0.035847260178985416,1,1,1]},"_eulerAngles":{"__type__":"cc.Vec3","x":174.21710924330242,"y":-89.95049452186797,"z":0.026409165399034724},"_is3DNode":true},{"__type__":"cc.Node","_name":"Bip001 L UpperArm","_parent":{"__id__":15},"_children":[{"__id__":17}],"_prefab":{"__type__":"cc.PrefabInfo","root":{"__id__":1},"asset":{"__uuid__":"65olQUWkxLHKiaTOYyk9UO"},"fileId":"233dAjW6JJjIb4zAW4o9SL"},"_trs":{"__type__":"TypedArray","ctor":"Float64Array","array":[0.0219580363482237,-2.22044599961948e-18,0,-0.33831480007298553,0.3557994947066086,0.1619656195778632,0.8559888747482977,1,1,1]},"_eulerAngles":{"__type__":"cc.Vec3","x":-44.019724791966254,"y":45.98779058050686,"z":2.0938857896344985},"_is3DNode":true},{"__type__":"cc.Node","_name":"Bip001 L Forearm","_parent":{"__id__":16},"_children":[{"__id__":18}],"_prefab":{"__type__":"cc.PrefabInfo","root":{"__id__":1},"asset":{"__uuid__":"65olQUWkxLHKiaTOYyk9UO"},"fileId":"d6mKH4WplCIIrKCNH3jz1V"},"_trs":{"__type__":"TypedArray","ctor":"Float64Array","array":[0.0468186065554619,0,9.53674295089968e-9,-2.3776692870113105e-17,1.4319247357344348e-17,-0.515905259527188,0.8566456462226285,1,1,1]},"_eulerAngles":{"__type__":"cc.Vec3","x":-3.180554662813841e-15,"y":-6.417707987086694e-30,"z":-62.11596601477231},"_is3DNode":true},{"__type__":"cc.Node","_name":"Bip001 L Hand","_parent":{"__id__":17},"_children":[{"__type__":"cc.Node","_name":"Bip001 L Finger0","_parent":{"__id__":18},"_prefab":{"__type__":"cc.PrefabInfo","root":{"__id__":1},"asset":{"__uuid__":"65olQUWkxLHKiaTOYyk9UO"},"fileId":"1cTTl0zOlNQInFeXKv2LO+"},"_trs":{"__type__":"TypedArray","ctor":"Float64Array","array":[0.0194225218147039,-1.77635679969558e-17,0,-0.001465325966251796,-0.0005170538324755168,0.08255002031895817,0.9965857111259856,1,1,1]},"_eulerAngles":{"__type__":"cc.Vec3","x":-0.1646944737535311,"y":-0.04581077555899824,"z":9.470388685346707},"_is3DNode":true}],"_prefab":{"__type__":"cc.PrefabInfo","root":{"__id__":1},"asset":{"__uuid__":"65olQUWkxLHKiaTOYyk9UO"},"fileId":"ceUMnuirNGcrUb0MT1uSZ0"},"_trs":{"__type__":"TypedArray","ctor":"Float64Array","array":[0.0423320569097996,-9.53674295089968e-9,3.55271359939116e-17,-0.5107503540710764,-0.2168736016992219,0.01738142173103456,0.8317438324874343,1,1,1]},"_eulerAngles":{"__type__":"cc.Vec3","x":-60.43645876608778,"y":-20.75074918184348,"z":14.504161298087892},"_is3DNode":true},{"__type__":"cc.Node","_name":"Bip001 R Clavicle","_parent":{"__id__":14},"_children":[{"__id__":20}],"_prefab":{"__type__":"cc.PrefabInfo","root":{"__id__":1},"asset":{"__uuid__":"65olQUWkxLHKiaTOYyk9UO"},"fileId":"2b5HXhWwFGEZOktBBDTGIL"},"_trs":{"__type__":"TypedArray","ctor":"Float64Array","array":[-0.00000566482549402281,0.0000209093086596113,-0.00657660095021129,-0.705909584483342,0.0358471485098194,0.7065033913197935,0.03549082320687387,1,1,1]},"_eulerAngles":{"__type__":"cc.Vec3","x":-174.21712706862223,"y":90.04951044071771,"z":-0.026408628743061168},"_is3DNode":true},{"__type__":"cc.Node","_name":"Bip001 R UpperArm","_parent":{"__id__":19},"_children":[{"__id__":21}],"_prefab":{"__type__":"cc.PrefabInfo","root":{"__id__":1},"asset":{"__uuid__":"65olQUWkxLHKiaTOYyk9UO"},"fileId":"6dDozvrp9OxocHlKlYbjj9"},"_trs":{"__type__":"TypedArray","ctor":"Float64Array","array":[0.0219580382108688,4.44089199923895e-18,3.55271359939116e-17,0.3000765457791678,-0.48206728869939774,0.06993991384350626,0.8201668149168296,1,1,1]},"_eulerAngles":{"__type__":"cc.Vec3","x":34.63780915987621,"y":-57.74861229730986,"z":-10.054763506895643},"_is3DNode":true},{"__type__":"cc.Node","_name":"Bip001 R Forearm","_parent":{"__id__":20},"_children":[{"__id__":22}],"_prefab":{"__type__":"cc.PrefabInfo","root":{"__id__":1},"asset":{"__uuid__":"65olQUWkxLHKiaTOYyk9UO"},"fileId":"52w107PU5Hob19nRpFM39/"},"_trs":{"__type__":"TypedArray","ctor":"Float64Array","array":[0.0468186065554619,9.53674295089968e-9,0,2.6521539124105536e-18,-2.2367715390026883e-18,-0.644705364392575,0.7644311565624711,1,1,1]},"_eulerAngles":{"__type__":"cc.Vec3","x":3.9756942007325054e-16,"y":-2.6162657898174435e-30,"z":-80.28717659611742},"_is3DNode":true},{"__type__":"cc.Node","_name":"Bip001 R Hand","_parent":{"__id__":21},"_children":[{"__type__":"cc.Node","_name":"Bip001 R Finger0","_parent":{"__id__":22},"_prefab":{"__type__":"cc.PrefabInfo","root":{"__id__":1},"asset":{"__uuid__":"65olQUWkxLHKiaTOYyk9UO"},"fileId":"2alhr30DBCUqfSdTMGCPL3"},"_trs":{"__type__":"TypedArray","ctor":"Float64Array","array":[0.0194225218147039,1.77635679969558e-17,1.77635679969558e-17,0.0014653560024260935,0.000517050864387694,0.08255002782456639,0.9965857104616508,1,1,1]},"_eulerAngles":{"__type__":"cc.Vec3","x":0.1646979796195795,"y":0.04581014266205926,"z":9.47038954926093},"_is3DNode":true}],"_prefab":{"__type__":"cc.PrefabInfo","root":{"__id__":1},"asset":{"__uuid__":"65olQUWkxLHKiaTOYyk9UO"},"fileId":"76Kd1NolxGCakiaO7aHsSv"},"_trs":{"__type__":"TypedArray","ctor":"Float64Array","array":[0.0423320457339287,9.53674295089968e-9,8.88178399847791e-18,0.564712052607521,0.10631145023725563,-0.01150240090814586,0.818331148106682,1,1,1]},"_eulerAngles":{"__type__":"cc.Vec3","x":68.66591674255193,"y":10.833337487256937,"z":5.810877328039666},"_is3DNode":true},{"__type__":"cc.Node","_name":"breakParticle","_parent":{"__id__":1},"_active":false,"_components":[{"__type__":"cc.ParticleSystem","node":{"__id__":23},"_materials":[{"__uuid__":"ecpdLyjvZBwrvm+cedCcQy"}],"_dstBlendFactor":1,"_custom":true,"_file":{"__uuid__":"73nCxGHgBJKJRwlZy43wHy"},"_stopped":false,"playOnLoad":false,"totalParticles":40,"duration":0.3,"emissionRate":80,"life":0.5,"lifeVar":0.3,"_startColor":{"__type__":"cc.Color","r":255,"g":255,"b":255},"_startColorVar":{"__type__":"cc.Color","a":140},"_endColor":{"__type__":"cc.Color","a":153},"_endColorVar":{"__type__":"cc.Color","a":63},"angle":180,"angleVar":180,"startSize":30,"startSizeVar":15,"endSize":30,"endSizeVar":5,"posVar":{"__type__":"cc.Vec2","x":20,"y":35},"_positionType":2,"positionType":2,"emitterMode":1,"startRadius":23,"endRadius":305}],"_prefab":{"__type__":"cc.PrefabInfo","root":{"__id__":1},"asset":{"__uuid__":"65olQUWkxLHKiaTOYyk9UO"},"fileId":"6aOWRHw41AX4n2aq70eRxY"},"_trs":{"__type__":"TypedArray","ctor":"Float64Array","array":[0,1,0,0,1,0,6.123233995736766e-17,0.00667,0.00667,0.00667]},"_eulerAngles":{"__type__":"cc.Vec3","y":180},"_is3DNode":true}]