{"__type__":"sp.SkeletonData","_name":"arrow_down2","_skeletonJson":{"skeleton":{"hash":"ME4mHHEDVXbn5rWu6pNx9oUGBRA","spine":"3.7.94","width":148,"height":246,"images":"","audio":""},"bones":[{"name":"root"},{"name":"arrow","parent":"root"},{"name":"arrow2","parent":"root"},{"name":"arrow3","parent":"root","y":33},{"name":"arrow4","parent":"root","y":154}],"slots":[{"name":"arrow","bone":"arrow","attachment":"arrow"},{"name":"arrow2","bone":"arrow2","attachment":"arrow"},{"name":"arrow3","bone":"arrow3","attachment":"arrow"},{"name":"arrow4","bone":"arrow4","attachment":"arrow"}],"skins":{"default":{"arrow":{"arrow":{"width":148,"height":92}},"arrow2":{"arrow":{"width":148,"height":92}},"arrow3":{"arrow":{"width":148,"height":92}},"arrow4":{"arrow":{"width":148,"height":92}}}},"animations":{"animation":{"slots":{"arrow":{"color":[{"time":0,"color":"ffffffff"},{"time":0.3333,"color":"ffffff00"}]},"arrow2":{"color":[{"time":0,"color":"ffffffca"},{"time":0.3333,"color":"ffffffff"},{"time":0.6667,"color":"ffffff00"}]},"arrow3":{"color":[{"time":0,"color":"ffffffab"},{"time":0.6667,"color":"ffffffff"},{"time":1,"color":"ffffff00"}]},"arrow4":{"color":[{"time":0,"color":"ffffff29"},{"time":0.6667,"color":"ffffffff"},{"time":1,"color":"ffffff00"}]}},"bones":{"arrow3":{"translate":[{"time":0,"x":0,"y":47.27},{"time":0.6667,"x":0,"y":-33},{"time":1,"x":0,"y":-63}]},"arrow2":{"translate":[{"time":0,"x":0,"y":29.34},{"time":0.3333,"x":0,"y":0},{"time":0.6667,"x":0,"y":-30}]},"arrow4":{"translate":[{"time":0,"x":0,"y":7.34},{"time":0.6667,"x":0,"y":-154},{"time":1,"x":0,"y":-184}]},"arrow":{"translate":[{"time":0,"x":0,"y":0},{"time":0.3333,"x":0,"y":-30}]}}}}},"_atlasText":"\narrow_down2.png\nsize: 256,128\nformat: RGBA8888\nfilter: Linear,Linear\nrepeat: none\narrow\n  rotate: false\n  xy: 2, 2\n  size: 148, 92\n  orig: 148, 92\n  offset: 0, 0\n  index: -1\n","textures":[{"__uuid__":"cf0O0vH15Lg4zWVIWdxS/2"}],"textureNames":["arrow_down2.png"]}